calculadoralohmz/__init__.py
calculadoralohmz/divisao.py
calculadoralohmz/multiplicacao.py
calculadoralohmz/soma.py
calculadoralohmz/subtracao.py
calculadoralohmz-0.0.2.dist-info/METADATA
calculadoralohmz-0.0.2.dist-info/WHEEL
calculadoralohmz-0.0.2.dist-info/top_level.txt
calculadoralohmz-0.0.2.dist-info/RECORD
