Metadata-Version: 2.1
Name: calculadoralohmz
Version: 0.0.2
Summary: Calculadora bem básica
Home-page: https://github.com/simonssilva/projeto-dio-calculadoralohmz
Author: simon
Author-email: simonssilva08@gmail.com
License: UNKNOWN
Platform: UNKNOWN
Requires-Python: >=3.8
